vector_demo/__init__.py
vector_demo/vector.py
vector_demo-0.3.1.dist-info/DESCRIPTION.rst
vector_demo-0.3.1.dist-info/METADATA
vector_demo-0.3.1.dist-info/RECORD
vector_demo-0.3.1.dist-info/WHEEL
vector_demo-0.3.1.dist-info/metadata.json
vector_demo-0.3.1.dist-info/top_level.txt
