Metadata-Version: 2.0
Name: vector-demo
Version: 0.3.1
Summary: A basic implementation of a Vector as a Python object.
Home-page: https://github.com/stephenflynn/vector_demo
Author: Stephen Flynn
Author-email: dev@stephenflynn.net
License: MIT license
Keywords: vector_demo
Platform: UNKNOWN
Classifier: Development Status :: 2 - Pre-Alpha
Classifier: Intended Audience :: Developers
Classifier: License :: OSI Approved :: MIT License
Classifier: Natural Language :: English
Classifier: Programming Language :: Python :: 3.4
Classifier: Programming Language :: Python :: 3.5
Requires-Python: >=3
